generic_preserver/__init__.py
generic_preserver/conflict_management.py
generic_preserver/metaclass.py
generic_preserver/pydantic_support.py
generic_preserver/utils.py
generic_preserver/wrapper.py
generic_preserver-0.1.6.dist-info/METADATA
generic_preserver-0.1.6.dist-info/WHEEL
generic_preserver-0.1.6.dist-info/licenses/LICENSE
generic_preserver-0.1.6.dist-info/RECORD
