Metadata-Version: 2.4
Name: generic-preserver
Version: 0.1.6
Summary: Extracting Generic Type References in Python
License-File: LICENSE
Author: Matthew Coulter
Author-email: mattcoul7@gmail.com
Requires-Python: >=3.9
Classifier: Programming Language :: Python :: 3
Classifier: Programming Language :: Python :: 3.9
Classifier: Programming Language :: Python :: 3.10
Classifier: Programming Language :: Python :: 3.11
Classifier: Programming Language :: Python :: 3.12
Classifier: Programming Language :: Python :: 3.13
Classifier: Programming Language :: Python :: 3.14
